LICENSE.md
README.md
requirements.txt
setup.cfg
setup.py
JaxHankel.egg-info/PKG-INFO
JaxHankel.egg-info/SOURCES.txt
JaxHankel.egg-info/dependency_links.txt
JaxHankel.egg-info/not-zip-safe
JaxHankel.egg-info/requires.txt
JaxHankel.egg-info/top_level.txt
jax_fht/__init__.py
jax_fht/cosmology.py
jax_fht/fht.py