Metadata-Version: 2.1
Name: JaxHankel
Version: 0.1.2
Summary: UNKNOWN
Home-page: https://github.com/florpi/JaxHankel
Author: Carolina Cuesta-Lazaro
Author-email: carolina.cuesta-lazaro@durham.ac.uk
License: Creative Commons Attribution-Noncommercial-Share Alike license
Platform: UNKNOWN
License-File: LICENSE.md
